MANIFEST.in
README.md
setup.py
waeasyapi/__init__.py
waeasyapi/cacert.pem
waeasyapi/client.py
waeasyapi/errors.py
waeasyapi.egg-info/PKG-INFO
waeasyapi.egg-info/SOURCES.txt
waeasyapi.egg-info/dependency_links.txt
waeasyapi.egg-info/requires.txt
waeasyapi.egg-info/top_level.txt
waeasyapi/constants/__init__.py
waeasyapi/constants/error_code.py
waeasyapi/constants/http_status_code.py
waeasyapi/constants/url.py
waeasyapi/resources/__init__.py
waeasyapi/resources/base.py
waeasyapi/resources/media.py
waeasyapi/resources/message.py
waeasyapi/resources/profile.py
waeasyapi/resources/template.py
waeasyapi/utility/__init__.py
waeasyapi/utility/utility.py