Metadata-Version: 2.1
Name: waeasyapi
Version: 2.0.0
Summary: WA Easy API Python Client
Home-page: https://github.com/waeasyapi/waeasyapi-python
Author: WA Easy API
License: MIT
Keywords: waeasyapi,whatsapp business apis,waba,whatsapp
Platform: UNKNOWN
Classifier: Development Status :: 4 - Beta
Classifier: Intended Audience :: Developers
Classifier: License :: OSI Approved :: MIT License
Classifier: Programming Language :: Python
Classifier: Programming Language :: Python :: 2
Classifier: Programming Language :: Python :: 2.7
Classifier: Programming Language :: Python :: 3
Classifier: Programming Language :: Python :: 3.4
Classifier: Programming Language :: Python :: 3.5
Classifier: Programming Language :: Python :: 3.6
Classifier: Topic :: Software Development :: Libraries :: Python Modules
